{
  "version": "0.9.10kc",
  "phase": "H",
  "low_32_policy": "bundled in core game only",
  "packages": [
    {
      "tier": "standard_64",
      "zip_name": "mechanist_generated_art_payload_0.9.10kc_standard_64.zip",
      "zip_path": "/mnt/data/mechanist_generated_art_payload_0.9.10kc_standard_64.zip",
      "zip_bytes": 48169743,
      "zip_size_mb": 45.94,
      "png_count": 2780,
      "sha256": "5418beb2dc1d1a8ffe1972a9f43628b1f416fe44dd89bdbd7c143aa4fe52345b",
      "mount_root_after_extract": "extract_zip_root",
      "runtime_tier_value": "standard_64"
    },
    {
      "tier": "intermediate_128",
      "zip_name": "mechanist_generated_art_payload_0.9.10kc_intermediate_128.zip",
      "zip_path": "/mnt/data/mechanist_generated_art_payload_0.9.10kc_intermediate_128.zip",
      "zip_bytes": 175958089,
      "zip_size_mb": 167.81,
      "png_count": 2780,
      "sha256": "7738f8e0f707cc5e5eeea7cf17894d9a13513923113d3786968fdb24d71fc585",
      "mount_root_after_extract": "extract_zip_root",
      "runtime_tier_value": "intermediate_128"
    },
    {
      "tier": "high_native",
      "zip_name": "mechanist_generated_art_payload_0.9.10kc_high_native.zip",
      "zip_path": "/mnt/data/mechanist_generated_art_payload_0.9.10kc_high_native.zip",
      "zip_bytes": 641532058,
      "zip_size_mb": 611.81,
      "png_count": 2780,
      "sha256": "81946719115c7acdcc6410d87cbb9b2c64c1a4f9f169ff61c6df9572154fd75e",
      "mount_root_after_extract": "extract_zip_root",
      "runtime_tier_value": "high_native"
    }
  ]
}